shifterator/__init__.py
shifterator/entropy.py
shifterator/helper.py
shifterator/plotting.py
shifterator/shifterator.py
shifterator/shifts.py
shifterator/lexicons/NRC-VAD/NRC-VAD_arousal_Afrikaans.tsv
shifterator/lexicons/NRC-VAD/NRC-VAD_arousal_Albanian.tsv
shifterator/lexicons/NRC-VAD/NRC-VAD_arousal_Amharic.tsv
shifterator/lexicons/NRC-VAD/NRC-VAD_arousal_Arabic.tsv
shifterator/lexicons/NRC-VAD/NRC-VAD_arousal_Armenian.tsv
shifterator/lexicons/NRC-VAD/NRC-VAD_arousal_Azeerbaijani.tsv
shifterator/lexicons/NRC-VAD/NRC-VAD_arousal_Basque.tsv
shifterator/lexicons/NRC-VAD/NRC-VAD_arousal_Belarusian.tsv
shifterator/lexicons/NRC-VAD/NRC-VAD_arousal_Bengali.tsv
shifterator/lexicons/NRC-VAD/NRC-VAD_arousal_Bosnian.tsv
shifterator/lexicons/NRC-VAD/NRC-VAD_arousal_Bulgarian.tsv
shifterator/lexicons/NRC-VAD/NRC-VAD_arousal_Catalan.tsv
shifterator/lexicons/NRC-VAD/NRC-VAD_arousal_Cebuano.tsv
shifterator/lexicons/NRC-VAD/NRC-VAD_arousal_Chinese-Simplified.tsv
shifterator/lexicons/NRC-VAD/NRC-VAD_arousal_Chinese-Traditional.tsv
shifterator/lexicons/NRC-VAD/NRC-VAD_arousal_Corsican.tsv
shifterator/lexicons/NRC-VAD/NRC-VAD_arousal_Croatian.tsv
shifterator/lexicons/NRC-VAD/NRC-VAD_arousal_Czech.tsv
shifterator/lexicons/NRC-VAD/NRC-VAD_arousal_Danish.tsv
shifterator/lexicons/NRC-VAD/NRC-VAD_arousal_Dutch.tsv
shifterator/lexicons/NRC-VAD/NRC-VAD_arousal_English.tsv
shifterator/lexicons/NRC-VAD/NRC-VAD_arousal_Esperanto.tsv
shifterator/lexicons/NRC-VAD/NRC-VAD_arousal_Estonian.tsv
shifterator/lexicons/NRC-VAD/NRC-VAD_arousal_Finnish.tsv
shifterator/lexicons/NRC-VAD/NRC-VAD_arousal_French.tsv
shifterator/lexicons/NRC-VAD/NRC-VAD_arousal_Frisian.tsv
shifterator/lexicons/NRC-VAD/NRC-VAD_arousal_Galician.tsv
shifterator/lexicons/NRC-VAD/NRC-VAD_arousal_Georgian.tsv
shifterator/lexicons/NRC-VAD/NRC-VAD_arousal_German.tsv
shifterator/lexicons/NRC-VAD/NRC-VAD_arousal_Greek.tsv
shifterator/lexicons/NRC-VAD/NRC-VAD_arousal_Gujarati.tsv
shifterator-0.3.0.dist-info/LICENSE.txt
shifterator-0.3.0.dist-info/METADATA
shifterator-0.3.0.dist-info/WHEEL
shifterator-0.3.0.dist-info/top_level.txt
shifterator-0.3.0.dist-info/RECORD
