Metadata-Version: 2.1
Name: shifterator
Version: 0.3.0
Summary: Interpretable data visualizations for understanding how texts differ at the word level
Home-page: https://github.com/ryanjgallagher/shifterator
Author: Ryan J. Gallagher
Author-email: gallagher.r@northeastern.edu
License: UNKNOWN
Keywords: natural language processing,sentiment analysis,information theory,computational social socience,digital humanities,text analysis,text as data,data visualization,data viz
Platform: UNKNOWN
Classifier: Programming Language :: Python
Classifier: Programming Language :: Python :: 3
Classifier: License :: OSI Approved :: Apache Software License
Classifier: Operating System :: OS Independent
Requires-Python: ~=3.6
License-File: LICENSE.txt
Requires-Dist: matplotlib
Requires-Dist: numpy
